cadati/__init__.py
cadati/cal_date.py
cadati/check_date.py
cadati/conv_doy.py
cadati/dekad.py
cadati/jd_date.py
cadati/np_date.py
cadati-0.0.6.dist-info/LICENSE.txt
cadati-0.0.6.dist-info/METADATA
cadati-0.0.6.dist-info/WHEEL
cadati-0.0.6.dist-info/top_level.txt
cadati-0.0.6.dist-info/RECORD
